{
  "content": [
    {
      "type": "paragraph",
      "children": [
        {
          "text": ""
        }
      ]
    },
    {
      "type": "event",
      "uuid": "736f529c-62be-4adc-900b-f37fb05f3923",
      "includes": [
        "media",
        "annotations",
        "description"
      ],
      "children": [
        {
          "text": ""
        }
      ]
    },
    {
      "type": "paragraph",
      "children": [
        {
          "text": ""
        }
      ]
    }
  ],
  "created_at": "2026-04-29T12:29:04.255Z",
  "created_by": "p-caceres-c",
  "title": "Afroperuanos",
  "slug": "afroperuanos",
  "updated_at": "2026-04-29T13:35:26.588Z",
  "updated_by": "p-caceres-c",
  "autogenerate": {
    "enabled": false,
    "type": "event",
    "type_id": "736f529c-62be-4adc-900b-f37fb05f3923"
  }
}